pretext_cli_redirect/__init__.py
pretext_cli-0.1.0.dist-info/WHEEL
pretext_cli-0.1.0.dist-info/METADATA
pretext_cli-0.1.0.dist-info/RECORD
